{"protocol":{"minReaderVersion":1,"minWriterVersion":2,"readerFeatures":null,"writerFeatures":null}}
{"metaData":{"id":"7dd2f31c-194c-45b8-849b-6466f198d5ab","format":{"provider":"parquet","options":{}},"schemaString":"{\"type\":\"struct\",\"fields\":[{\"name\":\"Name\",\"type\":\"string\",\"nullable\":true,\"metadata\":{}},{\"name\":\"Item\",\"type\":\"string\",\"nullable\":true,\"metadata\":{}},{\"name\":\"Kind\",\"type\":\"string\",\"nullable\":true,\"metadata\":{}},{\"name\":\"Hidden\",\"type\":\"boolean\",\"nullable\":true,\"metadata\":{}}]}","partitionColumns":[],"createdTime":1714035912170,"configuration":{}}}
{"commitInfo":{"operation":"ReplaceTable","engineInfo":"Mashup Engine/2.128.1031.0","additionalCommitInfo":null}}
{"add":{"path":"d40134f80e4d428cb1e21e549eaaa0ae.parquet","partitionValues":{},"size":340,"modificationTime":1714035913108,"dataChange":true,"stats":"{\"numRecords\":0,\"minValues\":{},\"maxValues\":{},\"nullCount\":{}}","tags":{"VORDER":"true"}}}
